certbot_dns_desec/__init__.py
certbot_dns_desec/dns_desec.py
certbot_dns_desec/dns_desec_test.py
certbot_dns_desec-1.3.2.dist-info/LICENSE.txt
certbot_dns_desec-1.3.2.dist-info/METADATA
certbot_dns_desec-1.3.2.dist-info/WHEEL
certbot_dns_desec-1.3.2.dist-info/entry_points.txt
certbot_dns_desec-1.3.2.dist-info/top_level.txt
certbot_dns_desec-1.3.2.dist-info/RECORD
