Metadata-Version: 2.2
Name: certbot-dns-desec
Version: 1.3.2
Summary: deSEC DNS Authenticator plugin for Certbot
Home-page: https://github.com/desec-io/certbot-dns-desec
Author: Nils Wisiol
Author-email: nils@desec.io
License: Apache License 2.0
Requires-Python: >=3.9
License-File: LICENSE.txt
Requires-Dist: certbot
Requires-Dist: dnspython
Requires-Dist: setuptools
Requires-Dist: requests
Dynamic: author
Dynamic: author-email
Dynamic: description
Dynamic: description-content-type
Dynamic: home-page
Dynamic: license
Dynamic: requires-dist
Dynamic: requires-python
Dynamic: summary
